fastjmd95/__init__.py
fastjmd95/_version.py
fastjmd95/jmd95numba.py
fastjmd95/jmd95wrapper.py
fastjmd95/test/__init__.py
fastjmd95/test/reference_values.py
fastjmd95/test/test_jmd95.py
fastjmd95-0.2.1.dist-info/LICENSE
fastjmd95-0.2.1.dist-info/METADATA
fastjmd95-0.2.1.dist-info/WHEEL
fastjmd95-0.2.1.dist-info/top_level.txt
fastjmd95-0.2.1.dist-info/RECORD
