Metadata-Version: 2.1
Name: fastjmd95
Version: 0.2.1
Summary: Numba version of Jackett & McDougall (1995) ocean equation of state.
Home-page: https://github.com/xgcm/fastjmd95
Author: fastjmd95 Developers
Author-email: rpa@ldeo.columbia.edu
License: MIT
Platform: UNKNOWN
Classifier: Development Status :: 4 - Beta
Classifier: License :: OSI Approved :: Apache Software License
Classifier: Operating System :: OS Independent
Classifier: Intended Audience :: Science/Research
Classifier: Programming Language :: Python
Classifier: Programming Language :: Python :: 3
Classifier: Programming Language :: Python :: 3.6
Classifier: Topic :: Scientific/Engineering
Requires-Python: >=3.6
Requires-Dist: numba
Provides-Extra: dask
Requires-Dist: dask ; extra == 'dask'
Provides-Extra: xarray
Requires-Dist: xarray ; extra == 'xarray'
